cardealerdp/__init__.py
cardealerdp/profile.py
cardealerdp/py.typed
cardealerdp/schemas/__init__.py
cardealerdp/schemas/car.py
cardealerdp/schemas/dealer.py
cardealerdp/schemas/showroom.py
cardealerdp-0.3.3.dist-info/METADATA
cardealerdp-0.3.3.dist-info/WHEEL
cardealerdp-0.3.3.dist-info/RECORD
