Metadata-Version: 2.4
Name: cardealerdp
Version: 0.3.3
Summary: Cardealer DP (Car Dealer Data Package) is a data exchange format that helps car dealerships share their car listings. It is developed on top of the Data Package standard
Project-URL: repository, https://github.com/datisthq/cardealerdp
Project-URL: homepage, https://datisthq.github.io/cardealerdp
Author: Evgeny Karev
License-Expression: MIT
Classifier: Programming Language :: Python :: 3
Classifier: Programming Language :: Python :: 3.12
Classifier: Topic :: Software Development :: Libraries :: Python Modules
Requires-Python: >=3.12
Requires-Dist: typing-extensions>=4.15
